shopifywebhookparser/__init__.py
shopifywebhookparser/__init__.pyi
shopifywebhookparser/models.py
shopifywebhookparser/models.pyi
shopifywebhookparser/parsing.py
shopifywebhookparser/parsing.pyi
shopify_webhook_parser_lib-0.1.21.dist-info/LICENSE
shopify_webhook_parser_lib-0.1.21.dist-info/METADATA
shopify_webhook_parser_lib-0.1.21.dist-info/WHEEL
shopify_webhook_parser_lib-0.1.21.dist-info/RECORD
