Metadata-Version: 2.1
Name: shopify-webhook-parser-lib
Version: 0.1.21
Summary: A Python module to parse Shopify webhook requests, tailored for Azure Functions.
Home-page: https://github.com/zinyosrim/shopify-webhook-parser-lib
License: MIT
Author: Zin Yosrim
Author-email: zinyosrim@gmail.com
Requires-Python: >=3.11,<4.0
Classifier: Intended Audience :: Developers
Classifier: License :: OSI Approved :: MIT License
Classifier: Operating System :: OS Independent
Classifier: Programming Language :: Python :: 3
Classifier: Programming Language :: Python :: 3.11
Classifier: Programming Language :: Python :: 3.12
Classifier: Topic :: Software Development :: Libraries :: Python Modules
Requires-Dist: azure-functions (>=1.17.0,<2.0.0)
Project-URL: Repository, https://github.com/zinyosrim/shopify-webhook-parser-lib
